gpioemu.v
/* verilator lint_off UNUSED */
/* verilator lint_off MULTIDRIVEN */

module gpioemu(n_reset,
    saddress[15:0], srd, swr,
    sdata_in[31:0], sdata_out[31:0],
    gpio_in[31:0], gpio_latch,
    gpio_out[31:0],
    clk,
    gpio_in_s_insp[31:0]);

    input           clk;
    input           n_reset;

    input [15:0]    saddress;
    input           srd;
    input           swr;
    input [31:0]    sdata_in;
    output[31:0]    sdata_out;
    reg [31:0]      sdata_out_s;


    input [31:0]    gpio_in;
    reg [31:0]      gpio_in_s;
    input           gpio_latch;
    output[31:0]    gpio_in_s_insp;

    output[31:0]    gpio_out;
    reg [31:0]      gpio_out_s;

    reg unsigned [48:0] result;
    reg unsigned[23:0] A2;
    reg unsigned[23:0] A1;
    reg unsigned[31:0] W;
    reg unsigned[23:0] L;
    reg unsigned[1:0] B;
    reg unsigned[15:0] operation_count;
    reg unsigned[3:0] state;
	reg unsigned valid;
    reg unsigned[23:0] tmp_ones_count;
    reg ready;
	reg done;
	

    localparam IDLE = 0,
              MULT = 1,
              COUNT_ONES = 2,
              DONE = 3;

    always @(negedge n_reset) begin
        gpio_in_s <= 0;
        gpio_out_s <= 0;
        sdata_out_s <= 0;
        state <= 4;
        result <=49'b0;
		W <= 32'b0;
        tmp_ones_count <= 0;
        operation_count <= 0;
        ready <= 1'b1;
        A1 <= 0;
        A2 <= 0;
        L <= 24'b0;
        B <= 2'b11;
		done <=1'b0;
    end
	
	
	

    always @(posedge swr) begin   // może być błąd
       
    if (saddress == 16'h03A0 ) begin
        ready <= 1'b1;
		done <=0;
		valid <=1'b1;
		B <= 2'b11;
        state <= IDLE;
        gpio_out_s <= gpio_out_s + 1; //licznik
    end
    if (saddress == 16'h37F) // adres pierwszego argumentu
        A1 <= sdata_in[23:0];
    else if (saddress == 16'h0388) // adres drugiego argumentu
        A2 <= sdata_in[23:0];
end



always @(posedge srd) begin
    if (saddress == 16'h390) begin
        if (done) begin
		W <= result[31:0];
            sdata_out_s <= W[31:0];
        end
    end 
	else if (saddress == 16'h3A0) begin
        sdata_out_s <= {30'b0, B};																	
    end 
	else if (saddress == 16'h398) begin
        sdata_out_s <= {8'h0, tmp_ones_count};
    end 
	else begin
        sdata_out_s <= 0;
    end
end



always @(posedge clk) begin
    case (state)
        IDLE: begin
            result <= 0;
			ready <= 1'b0;
			valid <=1'b1;
			W<=0;
			L<=0;
		
			B <= 2'b01;
			done <= 0;
            tmp_ones_count <= 0;
            state <= MULT;
        end
        MULT: begin
			ready <= 0;
            for (integer i = 0; i < 24; i = i + 1) begin
                if (A2[i]) begin
                    result <= result + ({25'h0, A1} << i);
                end
            end
			valid <= (result[48:32] == 0);
			W <= result [31:0];
			B <={ready,valid};
            state <= COUNT_ONES;
        end
        COUNT_ONES: begin
		 ready <=0;
		 B <={ready,valid};
		 tmp_ones_count = 0;
            for (integer i = 0; i < 32; i = i + 1) begin
                if (result[i]) begin
                    tmp_ones_count = tmp_ones_count + 1;
                end
            end
           
			B <={ready,valid};
			L = tmp_ones_count[23:0];
            state <= DONE;
        end
        DONE: begin
		done <= 1'b1;
            if (swr && saddress == 16'h03A0) begin // write B
                B <= sdata_in[2:1];
				
            end else if (swr && saddress == 16'h0398) begin // write L
               L <= sdata_in[23:0];
				
            end else if (swr && saddress == 16'h0390) begin // write W
                W <= sdata_in[31:0];
				
            end else begin
                state <= 4;
                ready <= 1'b1;
				
				
                operation_count <= operation_count + 1;
            end
        end
    endcase
end

assign gpio_out = {16'h0, operation_count[15:0]};
assign gpio_in_s_insp = gpio_in_s;
assign sdata_out = sdata_out_s;
endmodule

onl/gpioemu_tb.v
`timescale 1 ns/10 ps

module gpioemu_tb;

reg n_reset = 1;
reg [15:0] saddress = 0;
reg srd = 0;
reg swr = 0;
reg valid = 0;
reg [31:0] sdata_in = 0;
reg [31:0] gpio_in = 0;
reg gpio_latch = 0;
reg [31:0] gpio_out = 0;
reg clk = 0;
reg [31:0] gpio_in_s_insp = 0;

integer i;

initial begin
  $dumpfile("gpioemu.vcd");
  $dumpvars(0, gpioemu_tb);
  clk = 0;
end

initial begin

for(i=0;i<500;i=i+1)
#2 clk = ~clk;

end

initial begin
  // Reset
  #5 n_reset = 0;
  #5 n_reset = 1;

  // Simple check 2*8 =16
  // Add1
  #5 sdata_in = 32'h2;
  #5 saddress = 16'h037F;
  #5 swr = 1;
  #5 swr = 0;

  // Add2
  #5 sdata_in = 32'h8;
  #5 saddress = 16'h0388;
  #5 swr = 1;
  #5 swr = 0;

  // Control - start operation=
  #5 saddress = 16'h03A0;
  #5 swr = 1;
  #5 swr = 0;

  // Result
  #30 saddress = 16'h0390;
  #5 srd = 1;
  #5 srd = 0;
  ////////////////////////////////////////////////////////////
  
  
  
  
    // Reset
  #5 n_reset = 0;
  #5 n_reset = 1;

  // Simple check 16*128 =2048
  // Add1
  #5 sdata_in = 32'h10;
  #5 saddress = 16'h037F;
  #5 swr = 1;
  #5 swr = 0;

  // Add2
  #5 sdata_in = 32'h80;
  #5 saddress = 16'h0388;
  #5 swr = 1;
  #5 swr = 0;

  // Control - start operation=
  #5 saddress = 16'h03A0;
  #5 swr = 1;
  #5 swr = 0;

  // Result
  #30 saddress = 16'h0390;
  #5 srd = 1;
  #5 srd = 0;
  
  
  
    ////////////////////////////////////////////////////////////
  
  
  
  
    // Reset
  #5 n_reset = 0;
  #5 n_reset = 1;

  // Simple check 8 388 608*2048 =??? test sprawdza czy zmieni się wartosć B
  // Add1
  #5 sdata_in = 32'h80000;
  #5 saddress = 16'h037F;
  #5 swr = 1;
  #5 swr = 0;

  // Add2
  #5 sdata_in = 32'h8007;
  #5 saddress = 16'h0388;
  #5 swr = 1;
  #5 swr = 0;

  // Control - start operation=
  #5 saddress = 16'h03A0;
  #5 swr = 1;
  #5 swr = 0;

  // Result
  #30 saddress = 16'h0390;
  #5 srd = 1;
  #5 srd = 0;
  

end

wire [31:0] gpio_out_test;
wire [31:0] sdata_out_test;
wire [31:0] gpio_in_s_insp_test;

gpioemu e1(n_reset,
saddress,
srd,
swr,
sdata_in,
sdata_out_test,
gpio_in,
gpio_latch,
gpio_out_test,
clk,
gpio_in_s_insp_test);

initial begin
$display("At %t, gpio_out = %h, sdata_out = %h", $time, gpio_out_test, sdata_out_test);

end



endmodule

gpioemu.vcd
$date
	Thu May 04 14:40:33 2023
$end
$version
	Icarus Verilog
$end
$timescale
	10ps
$end
$scope module gpioemu_tb $end
$var wire 32 ! sdata_out_test [31:0] $end
$var wire 32 " gpio_out_test [31:0] $end
$var wire 32 # gpio_in_s_insp_test [31:0] $end
$var reg 1 $ clk $end
$var reg 32 % gpio_in [31:0] $end
$var reg 32 & gpio_in_s_insp [31:0] $end
$var reg 1 ' gpio_latch $end
$var reg 32 ( gpio_out [31:0] $end
$var reg 1 ) n_reset $end
$var reg 16 * saddress [15:0] $end
$var reg 32 + sdata_in [31:0] $end
$var reg 1 , srd $end
$var reg 1 - swr $end
$var reg 1 . valid $end
$var integer 32 / i [31:0] $end
$scope module e1 $end
$var wire 1 $ clk $end
$var wire 32 0 gpio_in [31:0] $end
$var wire 32 1 gpio_in_s_insp [31:0] $end
$var wire 1 ' gpio_latch $end
$var wire 1 ) n_reset $end
$var wire 16 2 saddress [15:0] $end
$var wire 32 3 sdata_in [31:0] $end
$var wire 32 4 sdata_out [31:0] $end
$var wire 1 , srd $end
$var wire 1 - swr $end
$var wire 32 5 gpio_out [31:0] $end
$var parameter 32 6 COUNT_ONES $end
$var parameter 32 7 DONE $end
$var parameter 32 8 IDLE $end
$var parameter 32 9 MULT $end
$var reg 24 : A1 [23:0] $end
$var reg 24 ; A2 [23:0] $end
$var reg 2 < B [1:0] $end
$var reg 24 = L [23:0] $end
$var reg 32 > W [31:0] $end
$var reg 1 ? done $end
$var reg 32 @ gpio_in_s [31:0] $end
$var reg 32 A gpio_out_s [31:0] $end
$var reg 16 B operation_count [15:0] $end
$var reg 1 C ready $end
$var reg 49 D result [48:0] $end
$var reg 32 E sdata_out_s [31:0] $end
$var reg 4 F state [3:0] $end
$var reg 24 G tmp_ones_count [23:0] $end
$var reg 1 H valid $end
$scope begin $ivl_for_loop0 $end
$var integer 32 I i [31:0] $end
$upscope $end
$scope begin $ivl_for_loop1 $end
$var integer 32 J i [31:0] $end
$upscope $end
$upscope $end
$upscope $end
$enddefinitions $end
$comment Show the parameter values. $end
$dumpall
b1 9
b0 8
b11 7
b10 6
$end
#0
$dumpvars
bx J
bx I
xH
bx G
bx F
bx E
bx D
xC
bx B
bx A
bx @
x?
bx >
bx =
bx <
bx ;
bx :
b0xxxxxxxxxxxxxxxx 5
bx 4
b0 3
b0 2
bx 1
b0 0
b0 /
0.
0-
0,
b0 +
b0 *
1)
b0 (
0'
b0 &
b0 %
0$
bx #
b0xxxxxxxxxxxxxxxx "
bx !
$end
#200
b1 /
1$
#400
b10 /
0$
#500
0?
b11 <
b0 =
b0 ;
b0 :
1C
b0 "
b0 5
b0 B
b0 G
b0 >
b0 D
b100 F
b0 !
b0 4
b0 E
b0 A
b0 #
b0 1
b0 @
0)
#600
b11 /
1$
#800
b100 /
0$
#1000
b101 /
1$
1)
#1200
b110 /
0$
#1400
b111 /
1$
#1500
b10 +
b10 3
#1600
b1000 /
0$
#1800
b1001 /
1$
#2000
b1010 /
0$
b1101111111 *
b1101111111 2
#2200
b1011 /
1$
#2400
b1100 /
0$
#2500
b10 :
1-
#2600
b1101 /
1$
#2800
b1110 /
0$
#3000
b1111 /
1$
0-
#3200
b10000 /
0$
#3400
b10001 /
1$
#3500
b1000 +
b1000 3
#3600
b10010 /
0$
#3800
b10011 /
1$
#4000
b10100 /
0$
b1110001000 *
b1110001000 2
#4200
b10101 /
1$
#4400
b10110 /
0$
#4500
b1000 ;
1-
#4600
b10111 /
1$
#4800
b11000 /
0$
#5000
b11001 /
1$
0-
#5200
b11010 /
0$
#5400
b11011 /
1$
#5500
b1110100000 *
b1110100000 2
#5600
b11100 /
0$
#5800
b11101 /
1$
#6000
b1 A
b0 F
1H
b11110 /
0$
1-
#6200
b1 F
b1 <
0C
b11111 /
1$
#6400
b100000 /
0$
#6500
0-
#6600
b10 F
b10000 D
b11000 I
b100001 /
1$
#6800
b100010 /
0$
#7000
b11 F
b1 =
b1 G
b100000 J
b100011 /
1$
#7200
b100100 /
0$
#7400
b1 "
b1 5
b1 B
1C
b100 F
1?
b100101 /
1$
#7600
b100110 /
0$
#7800
b100111 /
1$
#8000
b101000 /
0$
#8200
b101001 /
1$
#8400
b101010 /
0$
#8600
b101011 /
1$
#8800
b101100 /
0$
#9000
b101101 /
1$
#9200
b101110 /
0$
#9400
b101111 /
1$
#9500
b1110010000 *
b1110010000 2
#9600
b110000 /
0$
#9800
b110001 /
1$
#10000
b10000 >
b110010 /
0$
1,
#10200
b110011 /
1$
#10400
b110100 /
0$
#10500
0,
#10600
b110101 /
1$
#10800
b110110 /
0$
#11000
0?
b11 <
b0 =
b0 ;
b0 :
b0 "
b0 5
b0 B
b0 G
b0 >
b0 D
b0 A
b110111 /
1$
0)
#11200
b111000 /
0$
#11400
b111001 /
1$
#11500
1)
#11600
b111010 /
0$
#11800
b111011 /
1$
#12000
b111100 /
0$
b10000 +
b10000 3
#12200
b111101 /
1$
#12400
b111110 /
0$
#12500
b1101111111 *
b1101111111 2
#12600
b111111 /
1$
#12800
b1000000 /
0$
#13000
b10000 :
b1000001 /
1$
1-
#13200
b1000010 /
0$
#13400
b1000011 /
1$
#13500
0-
#13600
b1000100 /
0$
#13800
b1000101 /
1$
#14000
b1000110 /
0$
b10000000 +
b10000000 3
#14200
b1000111 /
1$
#14400
b1001000 /
0$
#14500
b1110001000 *
b1110001000 2
#14600
b1001001 /
1$
#14800
b1001010 /
0$
#15000
b10000000 ;
b1001011 /
1$
1-
#15200
b1001100 /
0$
#15400
b1001101 /
1$
#15500
0-
#15600
b1001110 /
0$
#15800
b1001111 /
1$
#16000
b1010000 /
0$
b1110100000 *
b1110100000 2
#16200
b1010001 /
1$
#16400
b1010010 /
0$
#16500
b1 A
b0 F
1-
#16600
b1 F
b1 <
0C
b1010011 /
1$
#16800
b1010100 /
0$
#17000
b10 F
b100000000000 D
b11000 I
b1010101 /
1$
0-
#17200
b1010110 /
0$
#17400
b11 F
b1 =
b1 G
b100000 J
b1010111 /
1$
#17600
b1011000 /
0$
#17800
b1 "
b1 5
b1 B
1C
b100 F
1?
b1011001 /
1$
#18000
b1011010 /
0$
#18200
b1011011 /
1$
#18400
b1011100 /
0$
#18600
b1011101 /
1$
#18800
b1011110 /
0$
#19000
b1011111 /
1$
#19200
b1100000 /
0$
#19400
b1100001 /
1$
#19600
b1100010 /
0$
#19800
b1100011 /
1$
#20000
b1100100 /
0$
b1110010000 *
b1110010000 2
#20200
b1100101 /
1$
#20400
b1100110 /
0$
#20500
b100000000000 >
1,
#20600
b1100111 /
1$
#20800
b1101000 /
0$
#21000
b1101001 /
1$
0,
#21200
b1101010 /
0$
#21400
b1101011 /
1$
#21500
0?
b11 <
b0 =
b0 ;
b0 :
b0 "
b0 5
b0 B
b0 G
b0 >
b0 D
b0 A
0)
#21600
b1101100 /
0$
#21800
b1101101 /
1$
#22000
b1101110 /
0$
1)
#22200
b1101111 /
1$
#22400
b1110000 /
0$
#22500
b10000000000000000000 +
b10000000000000000000 3
#22600
b1110001 /
1$
#22800
b1110010 /
0$
#23000
b1110011 /
1$
b1101111111 *
b1101111111 2
#23200
b1110100 /
0$
#23400
b1110101 /
1$
#23500
b10000000000000000000 :
1-
#23600
b1110110 /
0$
#23800
b1110111 /
1$
#24000
b1111000 /
0$
0-
#24200
b1111001 /
1$
#24400
b1111010 /
0$
#24500
b1000000000000111 +
b1000000000000111 3
#24600
b1111011 /
1$
#24800
b1111100 /
0$
#25000
b1111101 /
1$
b1110001000 *
b1110001000 2
#25200
b1111110 /
0$
#25400
b1111111 /
1$
#25500
b1000000000000111 ;
1-
#25600
b10000000 /
0$
#25800
b10000001 /
1$
#26000
b10000010 /
0$
0-
#26200
b10000011 /
1$
#26400
b10000100 /
0$
#26500
b1110100000 *
b1110100000 2
#26600
b10000101 /
1$
#26800
b10000110 /
0$
#27000
b1 A
b0 F
b10000111 /
1$
1-
#27200
b10001000 /
0$
#27400
b1 F
b1 <
0C
b10001001 /
1$
#27500
0-
#27600
b10001010 /
0$
#27800
b10 F
b10000000000000000000000000000000000 D
b11000 I
b10001011 /
1$
#28000
b10001100 /
0$
#28200
b11 F
b100000 J
b10001101 /
1$
#28400
b10001110 /
0$
#28600
b1 "
b1 5
b1 B
1C
b100 F
1?
b10001111 /
1$
#28800
b10010000 /
0$
#29000
b10010001 /
1$
#29200
b10010010 /
0$
#29400
b10010011 /
1$
#29600
b10010100 /
0$
#29800
b10010101 /
1$
#30000
b10010110 /
0$
#30200
b10010111 /
1$
#30400
b10011000 /
0$
#30500
b1110010000 *
b1110010000 2
#30600
b10011001 /
1$
#30800
b10011010 /
0$
#31000
b10011011 /
1$
1,
#31200
b10011100 /
0$
#31400
b10011101 /
1$
#31500
0,
#31600
b10011110 /
0$
#31800
b10011111 /
1$
#32000
b10100000 /
0$
#32200
b10100001 /
1$
#32400
b10100010 /
0$
#32600
b10100011 /
1$
#32800
b10100100 /
0$
#33000
b10100101 /
1$
#33200
b10100110 /
0$
#33400
b10100111 /
1$
#33600
b10101000 /
0$
#33800
b10101001 /
1$
#34000
b10101010 /
0$
#34200
b10101011 /
1$
#34400
b10101100 /
0$
#34600
b10101101 /
1$
#34800
b10101110 /
0$
#35000
b10101111 /
1$
#35200
b10110000 /
0$
#35400
b10110001 /
1$
#35600
b10110010 /
0$
#35800
b10110011 /
1$
#36000
b10110100 /
0$
#36200
b10110101 /
1$
#36400
b10110110 /
0$
#36600
b10110111 /
1$
#36800
b10111000 /
0$
#37000
b10111001 /
1$
#37200
b10111010 /
0$
#37400
b10111011 /
1$
#37600
b10111100 /
0$
#37800
b10111101 /
1$
#38000
b10111110 /
0$
#38200
b10111111 /
1$
#38400
b11000000 /
0$
#38600
b11000001 /
1$
#38800
b11000010 /
0$
#39000
b11000011 /
1$
#39200
b11000100 /
0$
#39400
b11000101 /
1$
#39600
b11000110 /
0$
#39800
b11000111 /
1$
#40000
b11001000 /
0$
#40200
b11001001 /
1$
#40400
b11001010 /
0$
#40600
b11001011 /
1$
#40800
b11001100 /
0$
#41000
b11001101 /
1$
#41200
b11001110 /
0$
#41400
b11001111 /
1$
#41600
b11010000 /
0$
#41800
b11010001 /
1$
#42000
b11010010 /
0$
#42200
b11010011 /
1$
#42400
b11010100 /
0$
#42600
b11010101 /
1$
#42800
b11010110 /
0$
#43000
b11010111 /
1$
#43200
b11011000 /
0$
#43400
b11011001 /
1$
#43600
b11011010 /
0$
#43800
b11011011 /
1$
#44000
b11011100 /
0$
#44200
b11011101 /
1$
#44400
b11011110 /
0$
#44600
b11011111 /
1$
#44800
b11100000 /
0$
#45000
b11100001 /
1$
#45200
b11100010 /
0$
#45400
b11100011 /
1$
#45600
b11100100 /
0$
#45800
b11100101 /
1$
#46000
b11100110 /
0$
#46200
b11100111 /
1$
#46400
b11101000 /
0$
#46600
b11101001 /
1$
#46800
b11101010 /
0$
#47000
b11101011 /
1$
#47200
b11101100 /
0$
#47400
b11101101 /
1$
#47600
b11101110 /
0$
#47800
b11101111 /
1$
#48000
b11110000 /
0$
#48200
b11110001 /
1$
#48400
b11110010 /
0$
#48600
b11110011 /
1$
#48800
b11110100 /
0$
#49000
b11110101 /
1$
#49200
b11110110 /
0$
#49400
b11110111 /
1$
#49600
b11111000 /
0$
#49800
b11111001 /
1$
#50000
b11111010 /
0$
#50200
b11111011 /
1$
#50400
b11111100 /
0$
#50600
b11111101 /
1$
#50800
b11111110 /
0$
#51000
b11111111 /
1$
#51200
b100000000 /
0$
#51400
b100000001 /
1$
#51600
b100000010 /
0$
#51800
b100000011 /
1$
#52000
b100000100 /
0$
#52200
b100000101 /
1$
#52400
b100000110 /
0$
#52600
b100000111 /
1$
#52800
b100001000 /
0$
#53000
b100001001 /
1$
#53200
b100001010 /
0$
#53400
b100001011 /
1$
#53600
b100001100 /
0$
#53800
b100001101 /
1$
#54000
b100001110 /
0$
#54200
b100001111 /
1$
#54400
b100010000 /
0$
#54600
b100010001 /
1$
#54800
b100010010 /
0$
#55000
b100010011 /
1$
#55200
b100010100 /
0$
#55400
b100010101 /
1$
#55600
b100010110 /
0$
#55800
b100010111 /
1$
#56000
b100011000 /
0$
#56200
b100011001 /
1$
#56400
b100011010 /
0$
#56600
b100011011 /
1$
#56800
b100011100 /
0$
#57000
b100011101 /
1$
#57200
b100011110 /
0$
#57400
b100011111 /
1$
#57600
b100100000 /
0$
#57800
b100100001 /
1$
#58000
b100100010 /
0$
#58200
b100100011 /
1$
#58400
b100100100 /
0$
#58600
b100100101 /
1$
#58800
b100100110 /
0$
#59000
b100100111 /
1$
#59200
b100101000 /
0$
#59400
b100101001 /
1$
#59600
b100101010 /
0$
#59800
b100101011 /
1$
#60000
b100101100 /
0$
#60200
b100101101 /
1$
#60400
b100101110 /
0$
#60600
b100101111 /
1$
#60800
b100110000 /
0$
#61000
b100110001 /
1$
#61200
b100110010 /
0$
#61400
b100110011 /
1$
#61600
b100110100 /
0$
#61800
b100110101 /
1$
#62000
b100110110 /
0$
#62200
b100110111 /
1$
#62400
b100111000 /
0$
#62600
b100111001 /
1$
#62800
b100111010 /
0$
#63000
b100111011 /
1$
#63200
b100111100 /
0$
#63400
b100111101 /
1$
#63600
b100111110 /
0$
#63800
b100111111 /
1$
#64000
b101000000 /
0$
#64200
b101000001 /
1$
#64400
b101000010 /
0$
#64600
b101000011 /
1$
#64800
b101000100 /
0$
#65000
b101000101 /
1$
#65200
b101000110 /
0$
#65400
b101000111 /
1$
#65600
b101001000 /
0$
#65800
b101001001 /
1$
#66000
b101001010 /
0$
#66200
b101001011 /
1$
#66400
b101001100 /
0$
#66600
b101001101 /
1$
#66800
b101001110 /
0$
#67000
b101001111 /
1$
#67200
b101010000 /
0$
#67400
b101010001 /
1$
#67600
b101010010 /
0$
#67800
b101010011 /
1$
#68000
b101010100 /
0$
#68200
b101010101 /
1$
#68400
b101010110 /
0$
#68600
b101010111 /
1$
#68800
b101011000 /
0$
#69000
b101011001 /
1$
#69200
b101011010 /
0$
#69400
b101011011 /
1$
#69600
b101011100 /
0$
#69800
b101011101 /
1$
#70000
b101011110 /
0$
#70200
b101011111 /
1$
#70400
b101100000 /
0$
#70600
b101100001 /
1$
#70800
b101100010 /
0$
#71000
b101100011 /
1$
#71200
b101100100 /
0$
#71400
b101100101 /
1$
#71600
b101100110 /
0$
#71800
b101100111 /
1$
#72000
b101101000 /
0$
#72200
b101101001 /
1$
#72400
b101101010 /
0$
#72600
b101101011 /
1$
#72800
b101101100 /
0$
#73000
b101101101 /
1$
#73200
b101101110 /
0$
#73400
b101101111 /
1$
#73600
b101110000 /
0$
#73800
b101110001 /
1$
#74000
b101110010 /
0$
#74200
b101110011 /
1$
#74400
b101110100 /
0$
#74600
b101110101 /
1$
#74800
b101110110 /
0$
#75000
b101110111 /
1$
#75200
b101111000 /
0$
#75400
b101111001 /
1$
#75600
b101111010 /
0$
#75800
b101111011 /
1$
#76000
b101111100 /
0$
#76200
b101111101 /
1$
#76400
b101111110 /
0$
#76600
b101111111 /
1$
#76800
b110000000 /
0$
#77000
b110000001 /
1$
#77200
b110000010 /
0$
#77400
b110000011 /
1$
#77600
b110000100 /
0$
#77800
b110000101 /
1$
#78000
b110000110 /
0$
#78200
b110000111 /
1$
#78400
b110001000 /
0$
#78600
b110001001 /
1$
#78800
b110001010 /
0$
#79000
b110001011 /
1$
#79200
b110001100 /
0$
#79400
b110001101 /
1$
#79600
b110001110 /
0$
#79800
b110001111 /
1$
#80000
b110010000 /
0$
#80200
b110010001 /
1$
#80400
b110010010 /
0$
#80600
b110010011 /
1$
#80800
b110010100 /
0$
#81000
b110010101 /
1$
#81200
b110010110 /
0$
#81400
b110010111 /
1$
#81600
b110011000 /
0$
#81800
b110011001 /
1$
#82000
b110011010 /
0$
#82200
b110011011 /
1$
#82400
b110011100 /
0$
#82600
b110011101 /
1$
#82800
b110011110 /
0$
#83000
b110011111 /
1$
#83200
b110100000 /
0$
#83400
b110100001 /
1$
#83600
b110100010 /
0$
#83800
b110100011 /
1$
#84000
b110100100 /
0$
#84200
b110100101 /
1$
#84400
b110100110 /
0$
#84600
b110100111 /
1$
#84800
b110101000 /
0$
#85000
b110101001 /
1$
#85200
b110101010 /
0$
#85400
b110101011 /
1$
#85600
b110101100 /
0$
#85800
b110101101 /
1$
#86000
b110101110 /
0$
#86200
b110101111 /
1$
#86400
b110110000 /
0$
#86600
b110110001 /
1$
#86800
b110110010 /
0$
#87000
b110110011 /
1$
#87200
b110110100 /
0$
#87400
b110110101 /
1$
#87600
b110110110 /
0$
#87800
b110110111 /
1$
#88000
b110111000 /
0$
#88200
b110111001 /
1$
#88400
b110111010 /
0$
#88600
b110111011 /
1$
#88800
b110111100 /
0$
#89000
b110111101 /
1$
#89200
b110111110 /
0$
#89400
b110111111 /
1$
#89600
b111000000 /
0$
#89800
b111000001 /
1$
#90000
b111000010 /
0$
#90200
b111000011 /
1$
#90400
b111000100 /
0$
#90600
b111000101 /
1$
#90800
b111000110 /
0$
#91000
b111000111 /
1$
#91200
b111001000 /
0$
#91400
b111001001 /
1$
#91600
b111001010 /
0$
#91800
b111001011 /
1$
#92000
b111001100 /
0$
#92200
b111001101 /
1$
#92400
b111001110 /
0$
#92600
b111001111 /
1$
#92800
b111010000 /
0$
#93000
b111010001 /
1$
#93200
b111010010 /
0$
#93400
b111010011 /
1$
#93600
b111010100 /
0$
#93800
b111010101 /
1$
#94000
b111010110 /
0$
#94200
b111010111 /
1$
#94400
b111011000 /
0$
#94600
b111011001 /
1$
#94800
b111011010 /
0$
#95000
b111011011 /
1$
#95200
b111011100 /
0$
#95400
b111011101 /
1$
#95600
b111011110 /
0$
#95800
b111011111 /
1$
#96000
b111100000 /
0$
#96200
b111100001 /
1$
#96400
b111100010 /
0$
#96600
b111100011 /
1$
#96800
b111100100 /
0$
#97000
b111100101 /
1$
#97200
b111100110 /
0$
#97400
b111100111 /
1$
#97600
b111101000 /
0$
#97800
b111101001 /
1$
#98000
b111101010 /
0$
#98200
b111101011 /
1$
#98400
b111101100 /
0$
#98600
b111101101 /
1$
#98800
b111101110 /
0$
#99000
b111101111 /
1$
#99200
b111110000 /
0$
#99400
b111110001 /
1$
#99600
b111110010 /
0$
#99800
b111110011 /
1$
#100000
b111110100 /
0$
